[
  {
    "name": "Hammering Fist Mastery",
    "tier_1": {
      "attacks": ["Stone-Shattering Fist"],
      "maneuvers": ["One-Two Punch"]
    },
    "tier_2": {
      "attacks": ["Snakebite Fist"],
      "maneuvers": ["Boxer's Guard"]
    }
  },
  { "name": "Unarmed Mastery 2" },
  { "name": "Unarmed Mastery 3" },
  { "name": "Grapple Mastery" },
  { "name": "Blade Mastery" },
  { "name": "Shield Mastery" },
  { "name": "Spear Mastery" },
  { "name": "Hafted Mastery" },
  { "name": "Ranged Mastery" },
  { "name": "Thrown Mastery" },
  { "name": "Jump Mastery" },
  { "name": "Tumble Mastery" }
]
